shapeaxi/._.DS_Store
shapeaxi/__about__.py
shapeaxi/__init__.py
shapeaxi/append_surf.py
shapeaxi/colors.py
shapeaxi/compute_min_scale.py
shapeaxi/dental_model_path.json
shapeaxi/dental_model_seg.py
shapeaxi/layers.py
shapeaxi/loss.py
shapeaxi/obj_to_vtk.py
shapeaxi/post_process.py
shapeaxi/saxi.py
shapeaxi/saxi_dataset.py
shapeaxi/saxi_eval.py
shapeaxi/saxi_eval_agg.py
shapeaxi/saxi_folds.py
shapeaxi/saxi_gradcam.py
shapeaxi/saxi_layers.py
shapeaxi/saxi_logger.py
shapeaxi/saxi_losses.py
shapeaxi/saxi_nets.py
shapeaxi/saxi_nets_lightning.py
shapeaxi/saxi_predict.py
shapeaxi/saxi_predict_v0.py
shapeaxi/saxi_train.py
shapeaxi/saxi_transforms.py
shapeaxi/split_train_eval.py
shapeaxi/utils.py
shapeaxi/Resources/__init__.py
shapeaxi/Resources/Icons/ASO.png
shapeaxi/Resources/UI/ASO.ui
shapeaxi/Resources/UI/ASO.ui.autosave
shapeaxi/notebooks/attention_shape_nn.ipynb
shapeaxi/notebooks/saxi_depth.ipynb
shapeaxi/notebooks/teeth_land_challenge.ipynb
shapeaxi/notebooks/test.ipynb
shapeaxi-1.1.1.dist-info/METADATA
shapeaxi-1.1.1.dist-info/WHEEL
shapeaxi-1.1.1.dist-info/entry_points.txt
shapeaxi-1.1.1.dist-info/licenses/LICENSE
shapeaxi-1.1.1.dist-info/RECORD
